setup.cfg
setup.py
clapi/__init__.py
clapi.egg-info/PKG-INFO
clapi.egg-info/SOURCES.txt
clapi.egg-info/dependency_links.txt
clapi.egg-info/top_level.txt