Metadata-Version: 1.1
Name: clapi
Version: 0.1.5
Summary: CLAPI wrapper
Home-page: https://github.com/rbw0/python-clapi
Author: Robert Wikman
Author-email: rbw@vault13.org
License: GPLv2
Download-URL: https://github.com/rbw0/python-clapi/tarball/0.1.5
Keywords: clapi,wrapper,Centreon
Platform: UNKNOWN
